ml_uncertainty/__init__.py
ml_uncertainty/cli.py
ml_uncertainty/error_propagation/__init__.py
ml_uncertainty/error_propagation/error_propagation.py
ml_uncertainty/error_propagation/statistical_utils.py
ml_uncertainty/model_inference/__init__.py
ml_uncertainty/model_inference/common_model_functions.py
ml_uncertainty/model_inference/ensemble_model_inference.py
ml_uncertainty/model_inference/gen_utils.py
ml_uncertainty/model_inference/parametric_model_inference.py
ml_uncertainty/non_linear_regression/__init__.py
ml_uncertainty/non_linear_regression/non_linear_regression.py
ml_uncertainty-0.1.1.dist-info/LICENSE
ml_uncertainty-0.1.1.dist-info/METADATA
ml_uncertainty-0.1.1.dist-info/WHEEL
ml_uncertainty-0.1.1.dist-info/entry_points.txt
ml_uncertainty-0.1.1.dist-info/top_level.txt
ml_uncertainty-0.1.1.dist-info/RECORD
