Metadata-Version: 2.1
Name: ml-uncertainty
Version: 0.1.1
Summary: Uncertainty quantification and model inference for machine learning models
Home-page: https://github.com/architdatar/ml_uncertainty
Author: Archit Nikhil Datar
Author-email: architdatar@gmail.com
License: MIT license
Keywords: ml_uncertainty
Platform: UNKNOWN
Classifier: Development Status :: 3 - Alpha
Classifier: Intended Audience :: Developers
Classifier: License :: OSI Approved :: MIT License
Classifier: Natural Language :: English
Classifier: Programming Language :: Python :: 3.9
Classifier: Programming Language :: Python :: 3.10
Classifier: Programming Language :: Python :: 3.11
Requires-Python: >=3.9,<=3.12
License-File: LICENSE
Requires-Dist: numpy>=1.17
Requires-Dist: scipy>=1.7
Requires-Dist: pandas>=1.5
Requires-Dist: scikit-learn>=1.0.2
Requires-Dist: autograd>=1.6.2
